{
    "target": "199.9.14.201",
    "measurement_filepath": "datasets/measurements/campaigns/199.9.14.201_North-Central-section_20230425/199.9.14.201_North-Central-section_1_52639768.json",
    "probes_filepath": "datasets/probes_section/North-Central-section_1.json",
    "alpha": 1,
    "threshold": 10.0,
    "noise": 0,
    "num_anycast_instances": 5,
    "anycast_instances": [
        {
            "marker": {
                "id": "QAR",
                "latitude": 52.0606002808,
                "longitude": 5.8730602264,
                "city": "Arnhem",
                "country_code": "NL"
            },
            "circle": {
                "id": "6863",
                "latitude": 52.5385,
                "longitude": 5.7005,
                "radius": 54.70905371023008
            }
        },
        {
            "marker": {
                "id": "BNX",
                "latitude": 50.4592018127,
                "longitude": 4.4538202286,
                "city": "Brussels",
                "country_code": "BE"
            },
            "circle": {
                "id": "6737",
                "latitude": 50.8805,
                "longitude": 4.4985,
                "radius": 101.97182937148577
            }
        },
        {
            "marker": {
                "id": "CGN",
                "latitude": 50.8658981323,
                "longitude": 7.1427397728,
                "city": "Cologne",
                "country_code": "DE"
            },
            "circle": {
                "id": "2325",
                "latitude": 50.1095,
                "longitude": 8.6785,
                "radius": 185.70749637547672
            }
        },
        {
            "marker": {
                "id": "HAM",
                "latitude": 53.6304016113,
                "longitude": 9.9882297516,
                "city": "Hamburg",
                "country_code": "DE"
            },
            "circle": {
                "id": "53696",
                "latitude": 54.3105,
                "longitude": 10.1315,
                "radius": 254.87343878991624
            }
        },
        {
            "marker": {
                "id": "BQH",
                "latitude": 51.3307991028,
                "longitude": 0.0324999988,
                "city": "London",
                "country_code": "GB"
            },
            "circle": {
                "id": "62907",
                "latitude": 50.7905,
                "longitude": 0.3175,
                "radius": 268.5398287450221
            }
        }
    ]
}