{
    "target": "199.9.14.201",
    "measurement_filepath": "datasets/measurements/campaigns/199.9.14.201_North-Central_20230410/199.9.14.201_North-Central_500_52069589.json",
    "probes_filepath": "datasets/probes_sets/North-Central_500.json",
    "alpha": 1,
    "threshold": 5.0,
    "noise": 0,
    "num_anycast_instances": 2,
    "anycast_instances": [
        {
            "marker": {
                "id": "AMX",
                "latitude": 52.3086013794,
                "longitude": 4.7638897896,
                "city": "Amsterdam",
                "country_code": "NL"
            },
            "circle": {
                "id": "1002178",
                "latitude": 52.3715,
                "longitude": 4.9005,
                "radius": 11.87361606664296
            }
        },
        {
            "marker": {
                "id": "GRQ",
                "latitude": 53.1197013855,
                "longitude": 6.5794401169,
                "city": "Groningen",
                "country_code": "NL"
            },
            "circle": {
                "id": "1002191",
                "latitude": 52.7175,
                "longitude": 6.2015,
                "radius": 80.80376871494087
            }
        }
    ]
}