{
    "target": "193.0.14.129",
    "measurement_filepath": "datasets/measurements/campaigns/193.0.14.129_North-Central-section_20230425/193.0.14.129_North-Central-section_1_52654511.json",
    "probes_filepath": "datasets/probes_section/North-Central-section_1.json",
    "alpha": 0.0,
    "threshold": -1,
    "noise": 0,
    "num_anycast_instances": 37,
    "anycast_instances": [
        {
            "marker": {
                "id": "SKP",
                "latitude": 41.9616012573,
                "longitude": 21.6214008331,
                "city": "Skopje",
                "country_code": "MK"
            },
            "circle": {
                "id": "6276",
                "latitude": 42.0005,
                "longitude": 21.4105,
                "radius": 27.36501809218275
            }
        },
        {
            "marker": {
                "id": "LED",
                "latitude": 59.8003005981,
                "longitude": 30.2625007629,
                "city": "St Petersburg",
                "country_code": "RU"
            },
            "circle": {
                "id": "17704",
                "latitude": 59.9795,
                "longitude": 30.3275,
                "radius": 31.8810542054375
            }
        },
        {
            "marker": {
                "id": "TBS",
                "latitude": 41.6692008972,
                "longitude": 44.95470047,
                "city": "Tbilisi",
                "country_code": "GE"
            },
            "circle": {
                "id": "11265",
                "latitude": 41.7195,
                "longitude": 44.7105,
                "radius": 32.78174317144125
            }
        },
        {
            "marker": {
                "id": "DEB",
                "latitude": 47.488899231,
                "longitude": 21.6152992249,
                "city": "Debrecen",
                "country_code": "HU"
            },
            "circle": {
                "id": "12454",
                "latitude": 47.5495,
                "longitude": 21.5995,
                "radius": 34.478980698351
            }
        },
        {
            "marker": {
                "id": "JAM",
                "latitude": 42.4548988342,
                "longitude": 26.3521995544,
                "city": "Yambol",
                "country_code": "BG"
            },
            "circle": {
                "id": "11518",
                "latitude": 42.1715,
                "longitude": 26.5675,
                "radius": 45.68570994113525
            }
        },
        {
            "marker": {
                "id": "FEL",
                "latitude": 48.2055549622,
                "longitude": 11.2669439316,
                "city": "F\u00fcrstenfeldbruck",
                "country_code": "DE"
            },
            "circle": {
                "id": "1002071",
                "latitude": 48.3675,
                "longitude": 10.9005,
                "radius": 49.8149388354555
            }
        },
        {
            "marker": {
                "id": "WMI",
                "latitude": 52.4510993958,
                "longitude": 20.6518001556,
                "city": "Warsaw",
                "country_code": "PL"
            },
            "circle": {
                "id": "17510",
                "latitude": 52.1875,
                "longitude": 20.9075,
                "radius": 51.07972574170025
            }
        },
        {
            "marker": {
                "id": "EVN",
                "latitude": 40.1473007202,
                "longitude": 44.3959007263,
                "city": "Yerevan",
                "country_code": "AM"
            },
            "circle": {
                "id": "10717",
                "latitude": 40.5505,
                "longitude": 44.7675,
                "radius": 57.972179195463745
            }
        },
        {
            "marker": {
                "id": "MHG",
                "latitude": 49.4730567932,
                "longitude": 8.514166832,
                "city": "Mannheim",
                "country_code": "DE"
            },
            "circle": {
                "id": "15710",
                "latitude": 49.8775,
                "longitude": 8.6575,
                "radius": 58.53683829010675
            }
        },
        {
            "marker": {
                "id": "RIX",
                "latitude": 56.9235992432,
                "longitude": 23.9710998535,
                "city": "Riga",
                "country_code": "LV"
            },
            "circle": {
                "id": "4016",
                "latitude": 56.9605,
                "longitude": 24.4275,
                "radius": 66.76981371981725
            }
        },
        {
            "marker": {
                "id": "KEF",
                "latitude": 63.9850006104,
                "longitude": -22.6056003571,
                "city": "Reykjav\u00edk",
                "country_code": "IS"
            },
            "circle": {
                "id": "1000959",
                "latitude": 64.0715,
                "longitude": -22.0205,
                "radius": 74.51791232277
            }
        },
        {
            "marker": {
                "id": "ZRH",
                "latitude": 47.4646987915,
                "longitude": 8.5491695404,
                "city": "Zurich",
                "country_code": "CH"
            },
            "circle": {
                "id": "30129",
                "latitude": 47.2115,
                "longitude": 7.5285,
                "radius": 86.11781937422124
            }
        },
        {
            "marker": {
                "id": "TZL",
                "latitude": 44.4586982727,
                "longitude": 18.7248001099,
                "city": "Tuzla",
                "country_code": "BA"
            },
            "circle": {
                "id": "51382",
                "latitude": 44.7385,
                "longitude": 19.7115,
                "radius": 92.14402252059375
            }
        },
        {
            "marker": {
                "id": "ORE",
                "latitude": 47.9878005981,
                "longitude": 1.7605600357,
                "city": "Orl\u00e9ans/Bricy",
                "country_code": "FR"
            },
            "circle": {
                "id": "31833",
                "latitude": 48.7885,
                "longitude": 1.9785,
                "radius": 94.2537744697115
            }
        },
        {
            "marker": {
                "id": "QGY",
                "latitude": 47.6244010925,
                "longitude": 17.8136005402,
                "city": "Gy\u0151r",
                "country_code": "HU"
            },
            "circle": {
                "id": "11590",
                "latitude": 47.4575,
                "longitude": 19.0415,
                "radius": 97.75396383903325
            }
        },
        {
            "marker": {
                "id": "PAR",
                "latitude": 49.0127983093,
                "longitude": 2.5499999523,
                "city": "Paris",
                "country_code": "FR"
            },
            "circle": {
                "id": "7071",
                "latitude": 49.2275,
                "longitude": 4.0305,
                "radius": 115.52453652755574
            }
        },
        {
            "marker": {
                "id": "POR",
                "latitude": 61.4617004395,
                "longitude": 21.7999992371,
                "city": "Pori",
                "country_code": "FI"
            },
            "circle": {
                "id": "51090",
                "latitude": 60.7975,
                "longitude": 23.6415,
                "radius": 135.35161052984375
            }
        },
        {
            "marker": {
                "id": "DHR",
                "latitude": 52.9234008789,
                "longitude": 4.7806200981,
                "city": "Den Helder",
                "country_code": "NL"
            },
            "circle": {
                "id": "6267",
                "latitude": 53.1105,
                "longitude": 6.8805,
                "radius": 142.86407226080848
            }
        },
        {
            "marker": {
                "id": "OSI",
                "latitude": 45.4626998901,
                "longitude": 18.8101997375,
                "city": "Osijek",
                "country_code": "HR"
            },
            "circle": {
                "id": "7175",
                "latitude": 46.2595,
                "longitude": 20.1505,
                "radius": 145.337285091194
            }
        },
        {
            "marker": {
                "id": "GRNET",
                "latitude": 37.9908372,
                "longitude": 23.7383394,
                "city": "Athens",
                "country_code": "GR"
            },
            "circle": {
                "id": "27903",
                "latitude": 38.2785,
                "longitude": 21.8275,
                "radius": 171.015408496268
            }
        },
        {
            "marker": {
                "id": "SLM",
                "latitude": 40.9520988464,
                "longitude": -5.5019898415,
                "city": "Salamanca",
                "country_code": "ES"
            },
            "circle": {
                "id": "60374",
                "latitude": 40.0995,
                "longitude": -4.0495,
                "radius": 175.02314649698374
            }
        },
        {
            "marker": {
                "id": "QVA",
                "latitude": 45.7421989441,
                "longitude": 8.8882303238,
                "city": "Varese",
                "country_code": "IT"
            },
            "circle": {
                "id": "21588",
                "latitude": 46.0915,
                "longitude": 11.1215,
                "radius": 181.93208853593725
            }
        },
        {
            "marker": {
                "id": "KSF",
                "latitude": 51.4083328247,
                "longitude": 9.3774995804,
                "city": "Kassel",
                "country_code": "DE"
            },
            "circle": {
                "id": "2112",
                "latitude": 50.8785,
                "longitude": 7.0975,
                "radius": 182.2355159774905
            }
        },
        {
            "marker": {
                "id": "YEO",
                "latitude": 51.0093994141,
                "longitude": -2.6388199329,
                "city": "Yeovil",
                "country_code": "GB"
            },
            "circle": {
                "id": "6499",
                "latitude": 52.2815,
                "longitude": -0.8685,
                "radius": 188.2400591187725
            }
        },
        {
            "marker": {
                "id": "OXF",
                "latitude": 51.8368988037,
                "longitude": -1.3200000525,
                "city": "Kidlington",
                "country_code": "GB"
            },
            "circle": {
                "id": "62907",
                "latitude": 50.7905,
                "longitude": 0.3175,
                "radius": 164.03545311882576
            }
        },
        {
            "marker": {
                "id": "QIE",
                "latitude": 43.5227012634,
                "longitude": 4.9238400459,
                "city": "Istres/Le Tub\u00e9",
                "country_code": "FR"
            },
            "circle": {
                "id": "34664",
                "latitude": 42.2495,
                "longitude": 3.1205,
                "radius": 204.16256119995398
            }
        },
        {
            "marker": {
                "id": "AER",
                "latitude": 43.4499015808,
                "longitude": 39.9566001892,
                "city": "Sochi",
                "country_code": "RU"
            },
            "circle": {
                "id": "7155",
                "latitude": 42.5095,
                "longitude": 41.8695,
                "radius": 211.46752907592548
            }
        },
        {
            "marker": {
                "id": "BUS",
                "latitude": 41.6102981567,
                "longitude": 41.5997009277,
                "city": "Batumi",
                "country_code": "GE"
            },
            "circle": {
                "id": "33775",
                "latitude": 42.1095,
                "longitude": 42.9205,
                "radius": 145.20054225628874
            }
        },
        {
            "marker": {
                "id": "BIQ",
                "latitude": 43.4683990479,
                "longitude": -1.5233199596,
                "city": "Biarritz/Anglet/Bayonne",
                "country_code": "FR"
            },
            "circle": {
                "id": "3471",
                "latitude": 41.6475,
                "longitude": -0.8895,
                "radius": 231.10404749709727
            }
        },
        {
            "marker": {
                "id": "KSD",
                "latitude": 59.4446983337,
                "longitude": 13.3374004364,
                "city": "Karlstad",
                "country_code": "SE"
            },
            "circle": {
                "id": "30735",
                "latitude": 59.3495,
                "longitude": 18.0685,
                "radius": 271.21575374069573
            }
        },
        {
            "marker": {
                "id": "UME",
                "latitude": 63.7918014526,
                "longitude": 20.2828006744,
                "city": "Ume\u00e5",
                "country_code": "SE"
            },
            "circle": {
                "id": "6658",
                "latitude": 65.0115,
                "longitude": 25.4695,
                "radius": 291.8755762431932
            }
        },
        {
            "marker": {
                "id": "CND",
                "latitude": 44.3622016907,
                "longitude": 28.4883003235,
                "city": "Constan\u0163a",
                "country_code": "RO"
            },
            "circle": {
                "id": "17286",
                "latitude": 46.8205,
                "longitude": 29.4815,
                "radius": 300.8266670319855
            }
        },
        {
            "marker": {
                "id": "VAA",
                "latitude": 63.0507011414,
                "longitude": 21.7621994019,
                "city": "Vaasa",
                "country_code": "FI"
            },
            "circle": {
                "id": "10638",
                "latitude": 64.2315,
                "longitude": 27.7285,
                "radius": 338.991670949561
            }
        },
        {
            "marker": {
                "id": "ABC",
                "latitude": 38.9485015869,
                "longitude": -1.8635200262,
                "city": "Albacete",
                "country_code": "ES"
            },
            "circle": {
                "id": "21570",
                "latitude": 37.3475,
                "longitude": -5.2295,
                "radius": 353.681801184019
            }
        },
        {
            "marker": {
                "id": "CEE",
                "latitude": 59.273601532,
                "longitude": 38.0158004761,
                "city": "Cherepovets",
                "country_code": "RU"
            },
            "circle": {
                "id": "1000969",
                "latitude": 54.6315,
                "longitude": 39.7105,
                "radius": 534.526205208275
            }
        },
        {
            "marker": {
                "id": "GML",
                "latitude": 50.6035003662,
                "longitude": 30.1919002533,
                "city": "Kiev",
                "country_code": "UA"
            },
            "circle": {
                "id": "11088",
                "latitude": 51.6815,
                "longitude": 39.2115,
                "radius": 648.0377852765897
            }
        },
        {
            "marker": {
                "id": "SAY",
                "latitude": 43.2563018799,
                "longitude": 11.2550001144,
                "city": "Siena",
                "country_code": "IT"
            },
            "circle": {
                "id": "1000401",
                "latitude": 37.5075,
                "longitude": 15.0775,
                "radius": 726.7616358888707
            }
        }
    ]
}