{
    "target": "198.97.190.53",
    "measurement_filepath": "datasets/measurements/campaigns/198.97.190.53_North-Central_20230410/198.97.190.53_North-Central_300_52071713.json",
    "probes_filepath": "datasets/probes_sets/North-Central_300.json",
    "alpha": 0.2,
    "threshold": -1,
    "noise": 0,
    "num_anycast_instances": 15,
    "anycast_instances": [
        {
            "marker": {
                "id": "QEF",
                "latitude": 49.9599990845,
                "longitude": 8.6458330154,
                "city": "Egelsbach",
                "country_code": "DE"
            },
            "circle": {
                "id": "20589",
                "latitude": 50.1015,
                "longitude": 8.6015,
                "radius": 26.94628297647125
            }
        },
        {
            "marker": {
                "id": "CSF",
                "latitude": 49.2535018921,
                "longitude": 2.5191400051,
                "city": "Creil",
                "country_code": "FR"
            },
            "circle": {
                "id": "1003879",
                "latitude": 48.8615,
                "longitude": 2.3405,
                "radius": 47.012403989957
            }
        },
        {
            "marker": {
                "id": "STN",
                "latitude": 51.8849983215,
                "longitude": 0.2349999994,
                "city": "London",
                "country_code": "GB"
            },
            "circle": {
                "id": "6559",
                "latitude": 51.5215,
                "longitude": -0.6405,
                "radius": 84.06517788835251
            }
        },
        {
            "marker": {
                "id": "QAM",
                "latitude": 49.8730010986,
                "longitude": 2.3870699406,
                "city": "Amiens/Glisy",
                "country_code": "FR"
            },
            "circle": {
                "id": "1004867",
                "latitude": 51.0205,
                "longitude": 2.1605,
                "radius": 143.053765938608
            }
        },
        {
            "marker": {
                "id": "MXP",
                "latitude": 45.6305999756,
                "longitude": 8.7281103134,
                "city": "Milan",
                "country_code": "IT"
            },
            "circle": {
                "id": "1002086",
                "latitude": 47.3805,
                "longitude": 8.5415,
                "radius": 216.90516467912948
            }
        },
        {
            "marker": {
                "id": "HAM",
                "latitude": 53.6304016113,
                "longitude": 9.9882297516,
                "city": "Hamburg",
                "country_code": "DE"
            },
            "circle": {
                "id": "6855",
                "latitude": 52.9295,
                "longitude": 9.2695,
                "radius": 229.50158186097272
            }
        },
        {
            "marker": {
                "id": "CGN",
                "latitude": 50.8658981323,
                "longitude": 7.1427397728,
                "city": "Cologne",
                "country_code": "DE"
            },
            "circle": {
                "id": "13934",
                "latitude": 52.3295,
                "longitude": 4.9185,
                "radius": 239.1704507423315
            }
        },
        {
            "marker": {
                "id": "LTN",
                "latitude": 51.8746986389,
                "longitude": -0.3683330119,
                "city": "London",
                "country_code": "GB"
            },
            "circle": {
                "id": "12174",
                "latitude": 53.4795,
                "longitude": -2.2495,
                "radius": 239.5285528334125
            }
        },
        {
            "marker": {
                "id": "TXL",
                "latitude": 52.5597000122,
                "longitude": 13.2876996994,
                "city": "Berlin",
                "country_code": "DE"
            },
            "circle": {
                "id": "32480",
                "latitude": 52.2275,
                "longitude": 21.1015,
                "radius": 564.8851006822747
            }
        },
        {
            "marker": {
                "id": "STR",
                "latitude": 48.6898994446,
                "longitude": 9.2219600677,
                "city": "Stuttgart",
                "country_code": "DE"
            },
            "circle": {
                "id": "61811",
                "latitude": 48.7675,
                "longitude": 11.4275,
                "radius": 221.73793152426126
            }
        },
        {
            "marker": {
                "id": "LED",
                "latitude": 59.8003005981,
                "longitude": 30.2625007629,
                "city": "St Petersburg",
                "country_code": "RU"
            },
            "circle": {
                "id": "1004826",
                "latitude": 60.4005,
                "longitude": 25.0285,
                "radius": 870.597897616916
            }
        },
        {
            "marker": {
                "id": "TOJ",
                "latitude": 40.4967002869,
                "longitude": -3.4458699226,
                "city": "Madrid",
                "country_code": "ES"
            },
            "circle": {
                "id": "1001379",
                "latitude": 38.7615,
                "longitude": -9.2595,
                "radius": 1391.369962118666
            }
        },
        {
            "marker": {
                "id": "DUB",
                "latitude": 53.4212989807,
                "longitude": -6.270070076,
                "city": "Dublin",
                "country_code": "IE"
            },
            "circle": {
                "id": "54607",
                "latitude": 64.0505,
                "longitude": -21.9925,
                "radius": 1564.5465744446562
            }
        },
        {
            "marker": {
                "id": "IST",
                "latitude": 40.9768981934,
                "longitude": 28.8145999908,
                "city": "Istanbul",
                "country_code": "TR"
            },
            "circle": {
                "id": "18864",
                "latitude": 35.1495,
                "longitude": 33.3505,
                "radius": 1926.1961471552274
            }
        },
        {
            "marker": {
                "id": "BUD",
                "latitude": 47.4369010925,
                "longitude": 19.2555999756,
                "city": "Budapest",
                "country_code": "HU"
            },
            "circle": {
                "id": "50818",
                "latitude": 48.2715,
                "longitude": 16.4075,
                "radius": 485.3218311875938
            }
        }
    ]
}