{
    "target": "192.36.148.17",
    "measurement_filepath": "datasets/measurements/campaigns/192.36.148.17_North-Central_20230410/192.36.148.17_North-Central_300_52072194.json",
    "probes_filepath": "datasets/probes_sets/North-Central_300.json",
    "alpha": 1,
    "threshold": 30.0,
    "noise": 0,
    "num_anycast_instances": 41,
    "anycast_instances": [
        {
            "marker": {
                "id": "NoCity",
                "latitude": 59.9415,
                "longitude": 10.8295,
                "city": "N/A",
                "country_code": "N/A"
            },
            "circle": {
                "id": "11148",
                "latitude": 59.9415,
                "longitude": 10.8295,
                "radius": 16.02733650581952
            }
        },
        {
            "marker": {
                "id": "NoCity",
                "latitude": 40.9475,
                "longitude": 17.2785,
                "city": "N/A",
                "country_code": "N/A"
            },
            "circle": {
                "id": "6621",
                "latitude": 40.9475,
                "longitude": 17.2785,
                "radius": 17.9773845156738
            }
        },
        {
            "marker": {
                "id": "DEX",
                "latitude": 50.121212,
                "longitude": 8.6365638,
                "city": "Frankfurt-am-Main",
                "country_code": "DE"
            },
            "circle": {
                "id": "1004293",
                "latitude": 50.1185,
                "longitude": 8.6815,
                "radius": 21.70690462262952
            }
        },
        {
            "marker": {
                "id": "TLL",
                "latitude": 59.4132995605,
                "longitude": 24.8327999115,
                "city": "Tallinn",
                "country_code": "EE"
            },
            "circle": {
                "id": "11447",
                "latitude": 59.4305,
                "longitude": 24.6995,
                "radius": 24.01858328079546
            }
        },
        {
            "marker": {
                "id": "SOF",
                "latitude": 42.6966934204,
                "longitude": 23.4114360809,
                "city": "Sofia",
                "country_code": "BG"
            },
            "circle": {
                "id": "27804",
                "latitude": 42.6595,
                "longitude": 23.3875,
                "radius": 27.845829733210017
            }
        },
        {
            "marker": {
                "id": "MUC",
                "latitude": 48.3538017273,
                "longitude": 11.7861003876,
                "city": "Munich",
                "country_code": "DE"
            },
            "circle": {
                "id": "1000720",
                "latitude": 48.1375,
                "longitude": 11.5785,
                "radius": 29.390078671915496
            }
        },
        {
            "marker": {
                "id": "PAR",
                "latitude": 49.0127983093,
                "longitude": 2.5499999523,
                "city": "Paris",
                "country_code": "FR"
            },
            "circle": {
                "id": "1003845",
                "latitude": 48.8995,
                "longitude": 2.2995,
                "radius": 30.130742920725723
            }
        },
        {
            "marker": {
                "id": "LHR",
                "latitude": 51.4706001282,
                "longitude": -0.4619410038,
                "city": "London",
                "country_code": "GB"
            },
            "circle": {
                "id": "1003887",
                "latitude": 51.5405,
                "longitude": -0.6685,
                "radius": 34.561750398080214
            }
        },
        {
            "marker": {
                "id": "CPH",
                "latitude": 55.6179008484,
                "longitude": 12.6560001373,
                "city": "Copenhagen",
                "country_code": "DK"
            },
            "circle": {
                "id": "53460",
                "latitude": 55.5975,
                "longitude": 13.0005,
                "radius": 37.333136807192524
            }
        },
        {
            "marker": {
                "id": "BBU",
                "latitude": 44.503200531,
                "longitude": 26.1021003723,
                "city": "Bucharest",
                "country_code": "RO"
            },
            "circle": {
                "id": "33742",
                "latitude": 44.3785,
                "longitude": 26.1395,
                "radius": 39.491210803653
            }
        },
        {
            "marker": {
                "id": "FICIX",
                "latitude": 60.1733244,
                "longitude": 24.9410248,
                "city": "Helsinki",
                "country_code": "FI"
            },
            "circle": {
                "id": "1004022",
                "latitude": 60.1685,
                "longitude": 24.9285,
                "radius": 40.66365713594688
            }
        },
        {
            "marker": {
                "id": "SXF",
                "latitude": 52.3800010681,
                "longitude": 13.5225000381,
                "city": "Berlin",
                "country_code": "DE"
            },
            "circle": {
                "id": "53252",
                "latitude": 52.5185,
                "longitude": 13.3295,
                "radius": 46.141431951352494
            }
        },
        {
            "marker": {
                "id": "MXP",
                "latitude": 45.6305999756,
                "longitude": 8.7281103134,
                "city": "Milan",
                "country_code": "IT"
            },
            "circle": {
                "id": "23189",
                "latitude": 46.0115,
                "longitude": 8.9315,
                "radius": 66.48715589975424
            }
        },
        {
            "marker": {
                "id": "RIX",
                "latitude": 56.9235992432,
                "longitude": 23.9710998535,
                "city": "Riga",
                "country_code": "LV"
            },
            "circle": {
                "id": "3732",
                "latitude": 56.8985,
                "longitude": 24.2085,
                "radius": 66.9309446711808
            }
        },
        {
            "marker": {
                "id": "ENS",
                "latitude": 52.2700004578,
                "longitude": 6.8741698265,
                "city": "Enschede",
                "country_code": "NL"
            },
            "circle": {
                "id": "1002108",
                "latitude": 52.2515,
                "longitude": 5.9975,
                "radius": 72.74741601186106
            }
        },
        {
            "marker": {
                "id": "ARN",
                "latitude": 59.6519012451,
                "longitude": 17.9186000824,
                "city": "Stockholm",
                "country_code": "SE"
            },
            "circle": {
                "id": "27955",
                "latitude": 59.3395,
                "longitude": 18.5695,
                "radius": 78.49708160120063
            }
        },
        {
            "marker": {
                "id": "PDV",
                "latitude": 42.0677986145,
                "longitude": 24.8507995605,
                "city": "Plovdiv",
                "country_code": "BG"
            },
            "circle": {
                "id": "16288",
                "latitude": 42.1515,
                "longitude": 24.7615,
                "radius": 106.03721296498804
            }
        },
        {
            "marker": {
                "id": "SCN",
                "latitude": 49.2145996094,
                "longitude": 7.1095099449,
                "city": "Saarbr\u00fccken",
                "country_code": "DE"
            },
            "circle": {
                "id": "54853",
                "latitude": 49.4985,
                "longitude": 5.9695,
                "radius": 107.8612042421025
            }
        },
        {
            "marker": {
                "id": "TMP",
                "latitude": 61.414100647,
                "longitude": 23.6044006348,
                "city": "Tampere/Pirkkala",
                "country_code": "FI"
            },
            "circle": {
                "id": "62779",
                "latitude": 61.4515,
                "longitude": 23.9005,
                "radius": 108.4567089827491
            }
        },
        {
            "marker": {
                "id": "ORB",
                "latitude": 59.2237014771,
                "longitude": 15.0380001068,
                "city": "\u00d6rebro",
                "country_code": "SE"
            },
            "circle": {
                "id": "50989",
                "latitude": 58.4215,
                "longitude": 15.6215,
                "radius": 112.47387695523125
            }
        },
        {
            "marker": {
                "id": "BNX",
                "latitude": 50.4592018127,
                "longitude": 4.4538202286,
                "city": "Brussels",
                "country_code": "BE"
            },
            "circle": {
                "id": "52709",
                "latitude": 51.0315,
                "longitude": 3.6775,
                "radius": 113.81509145175623
            }
        },
        {
            "marker": {
                "id": "OSR",
                "latitude": 49.6963005066,
                "longitude": 18.1110992432,
                "city": "Ostrava",
                "country_code": "CZ"
            },
            "circle": {
                "id": "20970",
                "latitude": 49.0675,
                "longitude": 18.9205,
                "radius": 115.37096933990755
            }
        },
        {
            "marker": {
                "id": "MIK",
                "latitude": 61.6865997314,
                "longitude": 27.2017993927,
                "city": "Mikkeli",
                "country_code": "FI"
            },
            "circle": {
                "id": "22068",
                "latitude": 62.2415,
                "longitude": 25.7605,
                "radius": 119.18348399093597
            }
        },
        {
            "marker": {
                "id": "STR",
                "latitude": 48.6898994446,
                "longitude": 9.2219600677,
                "city": "Stuttgart",
                "country_code": "DE"
            },
            "circle": {
                "id": "19810",
                "latitude": 48.7375,
                "longitude": 9.0975,
                "radius": 120.19817053805652
            }
        },
        {
            "marker": {
                "id": "SEN",
                "latitude": 51.5713996887,
                "longitude": 0.695555985,
                "city": "Southend",
                "country_code": "GB"
            },
            "circle": {
                "id": "1001420",
                "latitude": 50.9875,
                "longitude": 2.1285,
                "radius": 145.93327849354716
            }
        },
        {
            "marker": {
                "id": "AAR",
                "latitude": 56.2999992371,
                "longitude": 10.6190004349,
                "city": "Aarhus",
                "country_code": "DK"
            },
            "circle": {
                "id": "30715",
                "latitude": 55.5195,
                "longitude": 9.4575,
                "radius": 154.9155761782549
            }
        },
        {
            "marker": {
                "id": "ZAG",
                "latitude": 45.7429008484,
                "longitude": 16.0687999725,
                "city": "Zagreb",
                "country_code": "HR"
            },
            "circle": {
                "id": "52570",
                "latitude": 45.7375,
                "longitude": 14.1905,
                "radius": 155.5574348287575
            }
        },
        {
            "marker": {
                "id": "HAM",
                "latitude": 53.6304016113,
                "longitude": 9.9882297516,
                "city": "Hamburg",
                "country_code": "DE"
            },
            "circle": {
                "id": "6855",
                "latitude": 52.9295,
                "longitude": 9.2695,
                "radius": 159.59759088691908
            }
        },
        {
            "marker": {
                "id": "PRG",
                "latitude": 50.1007995605,
                "longitude": 14.2600002289,
                "city": "Prague",
                "country_code": "CZ"
            },
            "circle": {
                "id": "62603",
                "latitude": 50.0685,
                "longitude": 14.4075,
                "radius": 161.67045787096677
            }
        },
        {
            "marker": {
                "id": "GOT",
                "latitude": 57.6627998352,
                "longitude": 12.279800415,
                "city": "Gothenburg",
                "country_code": "SE"
            },
            "circle": {
                "id": "28329",
                "latitude": 57.1915,
                "longitude": 14.0585,
                "radius": 163.43536005460945
            }
        },
        {
            "marker": {
                "id": "LYS",
                "latitude": 45.726398468,
                "longitude": 5.0908298492,
                "city": "Lyon",
                "country_code": "FR"
            },
            "circle": {
                "id": "1003335",
                "latitude": 45.7695,
                "longitude": 4.8685,
                "radius": 172.96845443070228
            }
        },
        {
            "marker": {
                "id": "ZRH",
                "latitude": 47.4646987915,
                "longitude": 8.5491695404,
                "city": "Zurich",
                "country_code": "CH"
            },
            "circle": {
                "id": "51686",
                "latitude": 47.5605,
                "longitude": 7.5915,
                "radius": 137.33379179430875
            }
        },
        {
            "marker": {
                "id": "LJU",
                "latitude": 46.2237014771,
                "longitude": 14.4575996399,
                "city": "Ljubljana",
                "country_code": "SI"
            },
            "circle": {
                "id": "55566",
                "latitude": 46.5005,
                "longitude": 13.5805,
                "radius": 196.4746084588875
            }
        },
        {
            "marker": {
                "id": "WIE",
                "latitude": 48.1102981567,
                "longitude": 16.5697002411,
                "city": "Vienna",
                "country_code": "AT"
            },
            "circle": {
                "id": "60214",
                "latitude": 48.1795,
                "longitude": 16.8775,
                "radius": 151.30418029560036
            }
        },
        {
            "marker": {
                "id": "TRD",
                "latitude": 63.4578018188,
                "longitude": 10.9239997864,
                "city": "Trondheim",
                "country_code": "NO"
            },
            "circle": {
                "id": "53998",
                "latitude": 63.1615,
                "longitude": 14.7015,
                "radius": 285.8974523122725
            }
        },
        {
            "marker": {
                "id": "DUB",
                "latitude": 53.4212989807,
                "longitude": -6.270070076,
                "city": "Dublin",
                "country_code": "IE"
            },
            "circle": {
                "id": "30995",
                "latitude": 53.3295,
                "longitude": -6.2585,
                "radius": 291.3135478273692
            }
        },
        {
            "marker": {
                "id": "UME",
                "latitude": 63.7918014526,
                "longitude": 20.2828006744,
                "city": "Ume\u00e5",
                "country_code": "SE"
            },
            "circle": {
                "id": "50970",
                "latitude": 64.7475,
                "longitude": 20.9605,
                "radius": 344.37835982245247
            }
        },
        {
            "marker": {
                "id": "CKL",
                "latitude": 55.8782997131,
                "longitude": 38.0616989136,
                "city": "Moscow",
                "country_code": "RU"
            },
            "circle": {
                "id": "17658",
                "latitude": 55.6115,
                "longitude": 38.2095,
                "radius": 366.0969473571703
            }
        },
        {
            "marker": {
                "id": "ECV",
                "latitude": 40.3707008362,
                "longitude": -3.7851400375,
                "city": "Madrid",
                "country_code": "ES"
            },
            "circle": {
                "id": "1005309",
                "latitude": 40.1915,
                "longitude": -3.6725,
                "radius": 673.3428304583434
            }
        },
        {
            "marker": {
                "id": "NTE",
                "latitude": 47.1531982422,
                "longitude": -1.610730052,
                "city": "Nantes",
                "country_code": "FR"
            },
            "circle": {
                "id": "55718",
                "latitude": 48.0715,
                "longitude": -0.7625,
                "radius": 237.50308003904996
            }
        },
        {
            "marker": {
                "id": "BGW",
                "latitude": 33.2625007629,
                "longitude": 44.2346000671,
                "city": "Baghdad",
                "country_code": "IQ"
            },
            "circle": {
                "id": "1002236",
                "latitude": 40.1705,
                "longitude": 44.4885,
                "radius": 776.8450133881063
            }
        }
    ]
}